{"player": {"name": "player", "position": [3520, 2688], "max_hp": 200, "hp": 200, "normal_speed": 5, "speed": 5, "direction": [0.0, 0.0], "invincible": false, "invincible_time": 0, "invincible_cooldown": 400, "frame_index": 0.3, "animation_speed": 0.15, "status": "left_idle", "inventory": {"items": [{"type": "powerup", "name": "guard", "time": 0}, {"type": "powerup", "name": "dash", "time": 0}]}}, "enemies": [{"name": "spirit", "position": [3072, 1088], "max_hp": 50, "hp": 50, "normal_speed": 5, "speed": 5, "direction": [0.0, 0.0], "invincible": false, "invincible_time": 0, "invincible_cooldown": 400, "frame_index": 0.9, "animation_speed": 0.15, "status": "left_idle"}, {"name": "spirit", "position": [1600, 1152], "max_hp": 50, "hp": 50, "normal_speed": 5, "speed": 5, "direction": [0.0, 0.0], "invincible": false, "invincible_time": 0, "invincible_cooldown": 400, "frame_index": 0.9, "animation_speed": 0.15, "status": "left_idle"}, {"name": "spirit", "position": [4416, 1344], "max_hp": 50, "hp": 50, "normal_speed": 5, "speed": 5, "direction": [0.0, 0.0], "invincible": false, "invincible_time": 0, "invincible_cooldown": 400, "frame_index": 0.9, "animation_speed": 0.15, "status": "left_idle"}, {"name": "spirit", "position": [960, 1600], "max_hp": 50, "hp": 50, "normal_speed": 5, "speed": 5, "direction": [0.0, 0.0], "invincible": false, "invincible_time": 0, "invincible_cooldown": 400, "frame_index": 0.9, "animation_speed": 0.15, "status": "left_idle"}, {"name": "spirit", "position": [2432, 1600], "max_hp": 50, "hp": 50, "normal_speed": 5, "speed": 5, "direction": [0.0, 0.0], "invincible": false, "invincible_time": 0, "invincible_cooldown": 400, "frame_index": 0.9, "animation_speed": 0.15, "status": "left_idle"}, {"name": "spirit", "position": [3392, 1856], "max_hp": 50, "hp": 50, "normal_speed": 5, "speed": 5, "direction": [0.0, 0.0], "invincible": false, "invincible_time": 0, "invincible_cooldown": 400, "frame_index": 0.9, "animation_speed": 0.15, "status": "left_idle"}, {"name": "spirit", "position": [2240, 2112], "max_hp": 50, "hp": 50, "normal_speed": 5, "speed": 5, "direction": [0.0, 0.0], "invincible": false, "invincible_time": 0, "invincible_cooldown": 400, "frame_index": 0.9, "animation_speed": 0.15, "status": "left_idle"}, {"name": "spirit", "position": [3136, 2240], "max_hp": 50, "hp": 50, "normal_speed": 5, "speed": 5, "direction": [0.0, 0.0], "invincible": false, "invincible_time": 0, "invincible_cooldown": 400, "frame_index": 0.9, "animation_speed": 0.15, "status": "left_idle"}, {"name": "spirit", "position": [960, 2496], "max_hp": 50, "hp": 50, "normal_speed": 5, "speed": 5, "direction": [0.0, 0.0], "invincible": false, "invincible_time": 0, "invincible_cooldown": 400, "frame_index": 0.9, "animation_speed": 0.15, "status": "left_idle"}, {"name": "spirit", "position": [2752, 3072], "max_hp": 50, "hp": 50, "normal_speed": 5, "speed": 5, "direction": [0.0, 0.0], "invincible": false, "invincible_time": 0, "invincible_cooldown": 400, "frame_index": 0.9, "animation_speed": 0.15, "status": "left_idle"}, {"name": "spirit", "position": [896, 3584], "max_hp": 50, "hp": 50, "normal_speed": 5, "speed": 5, "direction": [0.0, 0.0], "invincible": false, "invincible_time": 0, "invincible_cooldown": 400, "frame_index": 0.9, "animation_speed": 0.15, "status": "left_idle"}]}